sql_flatmap/__init__.py
sql_flatmap/py.typed
sql_flatmap-0.0.0.dist-info/METADATA
sql_flatmap-0.0.0.dist-info/WHEEL
sql_flatmap-0.0.0.dist-info/RECORD
