Metadata-Version: 2.1
Name: sql-flatmap
Version: 0.0.0
Summary: A python package that performs automatic database uploading from flat objects and a schema mapping using an ORM.
Home-page: https://github.com/ekehoe32/sql-flatmap
Author: Eric Kehoe
Author-email: ekehoe32@gmail.com
Requires-Python: >=3.11,<4.0
Classifier: Programming Language :: Python :: 3
Classifier: Programming Language :: Python :: 3.11
Project-URL: Repository, https://github.com/ekehoe32/sql-flatmap
